ast_visualizer/__init__.py
ast_visualizer/main.py
ast_visualizer_marvel1337-0.0.1.dist-info/LICENSE
ast_visualizer_marvel1337-0.0.1.dist-info/METADATA
ast_visualizer_marvel1337-0.0.1.dist-info/WHEEL
ast_visualizer_marvel1337-0.0.1.dist-info/top_level.txt
ast_visualizer_marvel1337-0.0.1.dist-info/RECORD
