Metadata-Version: 2.1
Name: ast-visualizer-marvel1337
Version: 0.0.1
Summary: A small example package
Home-page: https://github.com/Atos1337/FluentPython-Homeworks/tree/main/hw_1
Author: Victor Samoilov
Author-email: victor.samoilov.2002@mail.ru
License: UNKNOWN
Platform: UNKNOWN
Classifier: Programming Language :: Python :: 3
Classifier: License :: OSI Approved :: MIT License
Classifier: Operating System :: OS Independent
Requires-Python: >=3.9
License-File: LICENSE
Requires-Dist: matplotlib (==3.4.3)
Requires-Dist: networkx (==2.6.3)
Requires-Dist: pydot (==1.4.2)
